augmento/__init__.py
augmento/main.py
augmento/augmentations/__init__.py
augmento/augmentations/affine.py
augmento/augmentations/colors.py
augmento/augmentations/flipper.py
augmento/augmentations/resizer.py
augmento/augmentations/rotator.py
augmento-0.0.1.dist-info/LICENSE.txt
augmento-0.0.1.dist-info/METADATA
augmento-0.0.1.dist-info/WHEEL
augmento-0.0.1.dist-info/top_level.txt
augmento-0.0.1.dist-info/RECORD
