Metadata-Version: 2.1
Name: augmento
Version: 0.0.1
Summary: Augmento is a Python library that provides a collection of image augmentation techniques for machine learning applications.
Home-page: https://github.com/rev9ai/augmento
Author: Syed Muhammad Asad
Author-email: asdkazmi@gmail.com
Classifier: Development Status :: 3 - Alpha
Classifier: Intended Audience :: Developers
Classifier: Natural Language :: English
Classifier: License :: OSI Approved :: MIT License
Classifier: Operating System :: OS Independent
Classifier: Programming Language :: Python
Classifier: Topic :: Software Development :: Libraries :: Python Modules
Requires-Python: >=3.6
License-File: LICENSE.txt
Requires-Dist: numpy
Requires-Dist: opencv-python
